Metadata-Version: 1.0
Name: jr-pypiexample
Version: 0.2
Summary: paquete de prueba, añadiendo la multiplicación
Home-page: https://github.com/joserracaswork/jr_pypiexample.git
Author: Joserracas
Author-email: joserracaswork@gmail.com
License: MIT
Platform: UNKNOWN
